<annotation>
	<folder>1_resized</folder>
	<filename>00220.jpg</filename>
	<path>/home/roberto/Documents/msc/msc-project/yolo_v4/ssl-dataset/1_resized/00220.jpg</path>
	<source>
		<database>Unknown</database>
	</source>
	<size>
		<width>224</width>
		<height>224</height>
		<depth>3</depth>
	</size>
	<segmented>0</segmented>
	<object>
		<name>robot</name>
		<pose>Unspecified</pose>
		<truncated>0</truncated>
		<difficult>0</difficult>
		<bndbox>
			<xmin>171</xmin>
			<ymin>160</ymin>
			<xmax>219</xmax>
			<ymax>205</ymax>
		</bndbox>
	</object>
	<object>
		<name>robot</name>
		<pose>Unspecified</pose>
		<truncated>0</truncated>
		<difficult>0</difficult>
		<bndbox>
			<xmin>4</xmin>
			<ymin>164</ymin>
			<xmax>52</xmax>
			<ymax>210</ymax>
		</bndbox>
	</object>
	<object>
		<name>robot</name>
		<pose>Unspecified</pose>
		<truncated>0</truncated>
		<difficult>0</difficult>
		<bndbox>
			<xmin>141</xmin>
			<ymin>94</ymin>
			<xmax>165</xmax>
			<ymax>117</ymax>
		</bndbox>
	</object>
	<object>
		<name>robot</name>
		<pose>Unspecified</pose>
		<truncated>0</truncated>
		<difficult>0</difficult>
		<bndbox>
			<xmin>36</xmin>
			<ymin>105</ymin>
			<xmax>63</xmax>
			<ymax>129</ymax>
		</bndbox>
	</object>
	<object>
		<name>robot</name>
		<pose>Unspecified</pose>
		<truncated>0</truncated>
		<difficult>0</difficult>
		<bndbox>
			<xmin>68</xmin>
			<ymin>106</ymin>
			<xmax>96</xmax>
			<ymax>129</ymax>
		</bndbox>
	</object>
	<object>
		<name>ball</name>
		<pose>Unspecified</pose>
		<truncated>0</truncated>
		<difficult>0</difficult>
		<bndbox>
			<xmin>83</xmin>
			<ymin>118</ymin>
			<xmax>92</xmax>
			<ymax>127</ymax>
		</bndbox>
	</object>
	<object>
		<name>robot</name>
		<pose>Unspecified</pose>
		<truncated>0</truncated>
		<difficult>0</difficult>
		<bndbox>
			<xmin>113</xmin>
			<ymin>139</ymin>
			<xmax>154</xmax>
			<ymax>175</ymax>
		</bndbox>
	</object>
	<object>
		<name>robot</name>
		<pose>Unspecified</pose>
		<truncated>0</truncated>
		<difficult>0</difficult>
		<bndbox>
			<xmin>134</xmin>
			<ymin>123</ymin>
			<xmax>166</xmax>
			<ymax>151</ymax>
		</bndbox>
	</object>
</annotation>
