<annotation>
	<folder>1_resized</folder>
	<filename>00134.jpg</filename>
	<path>/home/roberto/Documents/msc/msc-project/yolo_v4/ssl-dataset/1_resized/00134.jpg</path>
	<source>
		<database>Unknown</database>
	</source>
	<size>
		<width>224</width>
		<height>224</height>
		<depth>3</depth>
	</size>
	<segmented>0</segmented>
	<object>
		<name>robot</name>
		<pose>Unspecified</pose>
		<truncated>0</truncated>
		<difficult>0</difficult>
		<bndbox>
			<xmin>45</xmin>
			<ymin>47</ymin>
			<xmax>172</xmax>
			<ymax>176</ymax>
		</bndbox>
	</object>
	<object>
		<name>robot</name>
		<pose>Unspecified</pose>
		<truncated>1</truncated>
		<difficult>0</difficult>
		<bndbox>
			<xmin>1</xmin>
			<ymin>47</ymin>
			<xmax>31</xmax>
			<ymax>169</ymax>
		</bndbox>
	</object>
</annotation>
