<annotation>
	<folder>frames</folder>
	<filename>00458.jpg</filename>
	<path>/home/roberto/Documents/msc/msc-project/yolo_v4/ssl-dataset/1_resized/00458.jpg</path>
	<source>
		<database>Unknown</database>
	</source>
	<size>
		<width>224</width>
		<height>224</height>
		<depth>3</depth>
	</size>
	<segmented>0</segmented>
	<object>
		<name>robot</name>
		<pose>Unspecified</pose>
		<truncated>0</truncated>
		<difficult>0</difficult>
		<bndbox>
			<xmin>54</xmin>
			<ymin>74</ymin>
			<xmax>129</xmax>
			<ymax>159</ymax>
		</bndbox>
	</object>
	<object>
		<name>ball</name>
		<pose>Unspecified</pose>
		<truncated>0</truncated>
		<difficult>0</difficult>
		<bndbox>
			<xmin>191</xmin>
			<ymin>50</ymin>
			<xmax>199</xmax>
			<ymax>58</ymax>
		</bndbox>
	</object>
	<object>
		<name>goal</name>
		<pose>Unspecified</pose>
		<truncated>1</truncated>
		<difficult>0</difficult>
		<bndbox>
			<xmin>1</xmin>
			<ymin>27</ymin>
			<xmax>69</xmax>
			<ymax>53</ymax>
		</bndbox>
	</object>
	<object>
		<name>ball</name>
		<pose>Unspecified</pose>
		<truncated>0</truncated>
		<difficult>0</difficult>
		<bndbox>
			<xmin>22</xmin>
			<ymin>46</ymin>
			<xmax>30</xmax>
			<ymax>55</ymax>
		</bndbox>
	</object>
	<object>
		<name>robot</name>
		<pose>Unspecified</pose>
		<truncated>0</truncated>
		<difficult>0</difficult>
		<bndbox>
			<xmin>20</xmin>
			<ymin>30</ymin>
			<xmax>48</xmax>
			<ymax>56</ymax>
		</bndbox>
	</object>
	<object>
		<name>ball</name>
		<pose>Unspecified</pose>
		<truncated>0</truncated>
		<difficult>0</difficult>
		<bndbox>
			<xmin>89</xmin>
			<ymin>152</ymin>
			<xmax>115</xmax>
			<ymax>179</ymax>
		</bndbox>
	</object>
</annotation>
