<annotation>
	<folder>frames</folder>
	<filename>00500.jpg</filename>
	<path>/home/roberto/Documents/msc/msc-project/yolo_v4/ssl-dataset/1_resized/00500.jpg</path>
	<source>
		<database>Unknown</database>
	</source>
	<size>
		<width>224</width>
		<height>224</height>
		<depth>3</depth>
	</size>
	<segmented>0</segmented>
	<object>
		<name>ball</name>
		<pose>Unspecified</pose>
		<truncated>0</truncated>
		<difficult>0</difficult>
		<bndbox>
			<xmin>73</xmin>
			<ymin>153</ymin>
			<xmax>99</xmax>
			<ymax>179</ymax>
		</bndbox>
	</object>
	<object>
		<name>ball</name>
		<pose>Unspecified</pose>
		<truncated>0</truncated>
		<difficult>0</difficult>
		<bndbox>
			<xmin>134</xmin>
			<ymin>48</ymin>
			<xmax>142</xmax>
			<ymax>57</ymax>
		</bndbox>
	</object>
	<object>
		<name>robot</name>
		<pose>Unspecified</pose>
		<truncated>0</truncated>
		<difficult>0</difficult>
		<bndbox>
			<xmin>27</xmin>
			<ymin>81</ymin>
			<xmax>100</xmax>
			<ymax>164</ymax>
		</bndbox>
	</object>
</annotation>
